tacotui/__init__.py
tacotui/color.py
tacotui/getch.py
tacotui/screen.py
tacotui/version.py
tacotui/widgets.py
tacotui/demo/__init__.py
tacotui/demo/demo_color.py
tacotui/demo/demo_form.py
tacotui/demo/demo_game.py
tacotui/demo/demo_plot.py
tacotui/demo/demo_widgets.py
tacotui-0.1.dist-info/LICENSE.txt
tacotui-0.1.dist-info/METADATA
tacotui-0.1.dist-info/WHEEL
tacotui-0.1.dist-info/top_level.txt
tacotui-0.1.dist-info/RECORD
